inmanta_plugins/mysql/__init__.py
inmanta_plugins/mysql/setup.cfg
inmanta_plugins/mysql/files/mysql_create_db.service
inmanta_plugins/mysql/files/mysqld_sysconfig
inmanta_plugins/mysql/files/redhat_mysql_create_db
inmanta_plugins/mysql/files/ubuntu_mysql_create_db
inmanta_plugins/mysql/model/_init.cf
inmanta_plugins/mysql/templates/databases.tmpl
inmanta_plugins/mysql/templates/mariadb.cnf.tmpl
inmanta_plugins/mysql/templates/my.cnf.tmpl
inmanta_plugins/mysql/templates/my.cnf.ubuntu.tmpl
inmanta_module_mysql-0.6.15.dist-info/METADATA
inmanta_module_mysql-0.6.15.dist-info/WHEEL
inmanta_module_mysql-0.6.15.dist-info/top_level.txt
inmanta_module_mysql-0.6.15.dist-info/RECORD
