Metadata-Version: 2.1
Name: inmanta-module-mysql
Version: 0.6.15
License: Apache 2.0
Requires-Dist: inmanta-module-exec
Requires-Dist: inmanta-module-ip
Requires-Dist: inmanta-module-std
